<?xml version="1.0" encoding="utf-8"?>
<!DOCTYPE hibernate-mapping PUBLIC "-//Hibernate/Hibernate Mapping DTD 3.0//EN"
"http://hibernate.sourceforge.net/hibernate-mapping-3.0.dtd">
<!-- 
    Mapping file autogenerated by MyEclipse Persistence Tools
-->
<hibernate-mapping>
    <class name="com.gztydic.gateway.core.vo.GwNoticeVO" table="GW_NOTICE">
        <comment>公告信息</comment>
        <id name="noticeId" type="java.lang.Long">
            <column name="NOTICE_ID" precision="22" scale="0" />
            <generator class="sequence">
				<param name="sequence">SEQ_GW_NOTICE</param>
			</generator>
        </id>
        <property name="noticeTitle" type="java.lang.String">
            <column name="NOTICE_TITLE" length="200">
                <comment>公告标题</comment>
            </column>
        </property>
        <property name="noticeContent" type="java.lang.String">
            <column name="NOTICE_CONTENT" length="4000">
                <comment>公告内容</comment>
            </column>
        </property>
        <property name="createUser" type="java.lang.String">
            <column name="CREATE_USER" length="100">
                <comment>创建人</comment>
            </column>
        </property>
        <property name="createTime" type="java.util.Date">
            <column name="CREATE_TIME" length="10">
                <comment>创建时间</comment>
            </column>
        </property>
        <property name="updateUser" type="java.lang.String">
            <column name="UPDATE_USER" length="100">
                <comment>修改人</comment>
            </column>
        </property>
        <property name="updateTime" type="java.util.Date">
            <column name="UPDATE_TIME" length="10">
                <comment>修改时间</comment>
            </column>
        </property>
    </class>
</hibernate-mapping>
