<?xml version="1.0" encoding="utf-8"?>
<!DOCTYPE hibernate-mapping PUBLIC "-//Hibernate/Hibernate Mapping DTD 3.0//EN"
"http://hibernate.sourceforge.net/hibernate-mapping-3.0.dtd">
<!-- 
    Mapping file autogenerated by MyEclipse Persistence Tools
-->
<hibernate-mapping>
    <class name="com.gztydic.gateway.core.vo.GwSysCnfigVO" table="GW_SYS_CNFIG">
		<id name="configId" type="java.lang.Long">
            <column name="CONFIG_ID" precision="22" scale="0" />
            <generator class="sequence">
            	<param name="sequence">SEQ_GW_SYS_CNFIG</param>
            </generator>
        </id>
		<property column="CONFIG_TYPE" length="2" name="configType" type="java.lang.String"/>
		<property column="CONFIG_VALUE" name="configValue" type="java.lang.Long"/>
		<property column="CONFIG_UNIT" name="configUnit" type="java.lang.String"/>
    </class>
</hibernate-mapping>
